Homework/5/sram.v
`timescale 1ns/1ps

module sram (
    input  [8:0]  addr,       // 9-bit address for 512 locations
    inout  [15:0] data,       // 16-bit bidirectional data bus
    input         CE,         // Chip Enable (active low)
    input         OE,         // Output Enable (active low)
    input         WE,         // Write Enable (active low)
    input         UB,         // Upper Byte control (active low)
    input         LB          // Lower Byte control (active low)
);

    // -------------------- Timing numbers for the -10 part (ns) --------------------
    // Read path
    localparam integer tRC    = 10;
    localparam integer tAA    = 10;
    localparam integer tOHA   = 2;
    localparam integer tACE   = 10;
    localparam integer tDOE   = 4;
    localparam integer tHZOE  = 4;
    localparam integer tLZOE  = 0;
    localparam integer tHZCE  = 4;
    localparam integer tLZCE  = 3;
    localparam integer tBA    = 4;
    localparam integer tHZB   = 3;
    localparam integer tLZB   = 0;

    // Write path
    localparam integer tWC    = 10;
    localparam integer tSCE   = 8;
    localparam integer tAW    = 8;
    localparam integer tHA    = 0;
    localparam integer tPWB   = 8;
    localparam integer tPWE1  = 8;   // OE high
    localparam integer tPWE2  = 10;  // OE low
    localparam integer tSD    = 6;
    localparam integer tHD    = 0;
    localparam integer tHZWE  = 5;
    localparam integer tLZWE  = 2;

    // Effective behavioral delays
    localparam integer tREAD  = (tAA  > tACE) ? tAA  : tACE; // 10 ns
    localparam integer tWRITE = ( (tSCE > tAW ? tSCE : tAW) > tPWB )
                                ? (tSCE > tAW ? tSCE : tAW) : tPWB; // 8 ns

    // ------------------------------------------------------------------------------

    // Memory array: 512 locations, each 16 bits
    reg [15:0] mem [0:511];
    reg [15:0] data_output;

    // Invert active-low inputs to active-high internally
    wire CEx = ~CE, OEx = ~OE, WEx = ~WE, UBx = ~UB, LBx = ~LB;

    // Delayed gating network to model enable/disable (drive/Hi‑Z) timing *per control*
    wire ce_drv, oe_drv, we_drv, ub_drv, lb_drv;
    assign #(tLZCE, tHZCE) ce_drv = CEx;
    assign #(tLZOE, tHZOE) oe_drv = OEx;
    assign #(tLZWE, tHZWE) we_drv = WEx;
    assign #(tLZB,  tHZB ) ub_drv = UBx;
    assign #(tLZB,  tHZB ) lb_drv = LBx;

    // Drive condition seen on the external bus after proper enable/disable delays
    wire drive_bus = ce_drv && oe_drv && !we_drv && (ub_drv || lb_drv);

    // Tri-state data bus; the *timing of drive/Hi‑Z* is carried by the delayed enables above.
    // The value put on the bus comes from data_output (which itself respects tREAD).
    assign data = drive_bus ? data_output : 16'hzzzz;

    // Raw read/write intents (without the enable/disable edge timing)
    wire read_raw  = (CEx && !WEx && OEx && (UBx || LBx));
    wire write_raw = (CEx &&  WEx && (UBx || LBx));

    // ---------------------------- Read path ----------------------------
    // Update data_output after the proper read access delay.
    always @(*) begin
        if (read_raw) begin
            #(tREAD);
            if (UBx && LBx)
                data_output = mem[addr];                 // Full 16-bit read
            else if (UBx)
                data_output = {mem[addr][15:8], 8'hzz};  // Upper byte
            else if (LBx)
                data_output = {8'hzz, mem[addr][7:0]};   // Lower byte
            else
                data_output = 16'hzzzz;
        end
        // else: retain previous data_output (so the bus can hold tOHA when needed)
    end

    // ---------------------------- Write path ---------------------------
    // Commit the write after the proper write timing.
    always @(*) begin
        if (write_raw) begin
            #(tWRITE);
            if (UBx && LBx)
                mem[addr] = data;                   // Full 16-bit write
            else if (UBx)
                mem[addr][15:8] = data[15:8];       // Upper byte
            else if (LBx)
                mem[addr][7:0] = data[7:0];         // Lower byte
        end
    end

    // ---------------------------- Timing checks ------------------------
    specify
        // Path delays (for read)
        (addr *> data) = tAA;        // 10 ns delay from addr to data
        (CE   *> data) = tACE;
        (OE   *> data) = tDOE;
        (UB   *> data) = tBA;
        (LB   *> data) = tBA;

        // Write: setup/hold & pulse widths
        $setup (addr, posedge WE, tAW);
        $hold  (posedge WE, addr, tHA);

        $setup (data, posedge WE, tSD);
        $hold  (posedge WE, data, tHD);

        // WE pulse width (active low)
        $width (negedge WE, tPWB);

        // Optional cycle times (you can comment these if noisy)
        $period (posedge WE, tWC);   // Approximate write cycle
        $period (posedge OE, tRC);   // Approximate read cycle

        // CE low time for write (approximate, unconditional)
        $width (negedge CE, tSCE);
    endspecify

endmodule

Homework/5/sram_tb.v
`timescale 1ns/1ps

module tb_sram;
    reg  [8:0] addr;
    wire [15:0] data;
    reg           CE, OE, WE, UB, LB;
    reg  [15:0] data_out;
    wire [15:0] data_in;
    reg           drive_data;

    // Bidirectional data bus handling
    assign data = drive_data ? data_out : 16'hzzzz;
    assign data_in = data;

    // DUT
    sram uut (
        .addr(addr),
        .data(data),
        .CE(CE),
        .OE(OE),
        .WE(WE),
        .UB(UB),
        .LB(LB)
    );

    integer i;
    reg [15:0] ref_mem [0:29]; // for checking correctness

    // Task: Write full word to memory
    task write_word(input [8:0] a, input [15:0] d);
        begin
            addr       = a;
            data_out   = d;
            drive_data = 1;
            CE         = 0;
            OE         = 0;
            WE         = 0;  // Write
            UB         = 0;
            LB         = 0;
            #20;            // > tWC = 10ns + margin
            WE         = 1;
            drive_data = 0;
            #5;
        end
    endtask

    // Task: Read full word from memory
    task read_word(input [8:0] a);
        begin
            addr       = a;
            drive_data = 0;
            CE         = 0;
            OE         = 0;
            WE         = 1; // Read
            UB         = 0;
            LB         = 0;
            #20;             // > tRC = 10ns + margin
            $display("Read @%3d = 0x%04X", a, data_in);
        end
    endtask
    
    // Task: Read while staying in standby (CE must already be 1)
    // It does NOT change CE/OE/WE, it just samples the bus.
    task read_word_standby(input [8:0] a);
        begin
            addr       = a;
            drive_data = 0;   // never drive during a read
            // keep CE = 1 (standby), WE/OE as they currently are
            #20;              // just wait a little to sample
            $display("Read (standby) @%0d = %0h", a, data_in);
            if (data_in === 16'hzzzz)
                $display("   Correct: bus is Hi-Z in standby");
            else
                $display("   Error: expected Hi-Z (zzzz), got %0h", data_in);
        end
    endtask


    initial begin
        // VCD dumping setup
        // $dumpfile("sram_waveform.vcd"); // Specify the VCD file name
        // $dumpvars(0, tb_sram); // Dump all signals in the tb_sram module.
                               // 0 means dump all levels of hierarchy.
        // Init control signals
        addr       = 0;
        data_out   = 0;
        drive_data = 0;
        CE = 1;
        OE = 1;
        WE = 1;
        UB = 1;
        LB = 1;

        $display("\n--- Writing lower byte = addr to addresses 0-9 ---");
        for (i = 0; i < 10; i = i + 1) begin
            ref_mem[i] = {8'h00, i[7:0]};
            write_word(i, ref_mem[i]);
        end

        $display("\n--- Writing upper byte = $clog2(addr) to addresses 10-19 ---");
        for (i = 10; i < 20; i = i + 1) begin
            ref_mem[i] = {$clog2(i), 8'h00};
            write_word(i, ref_mem[i]);
        end

        $display("\n--- Writing random 16-bit values to addresses 20-29 ---");
        for (i = 20; i < 30; i = i + 1) begin
            ref_mem[i] = $random;
            write_word(i, ref_mem[i]);
        end

        $display("\n--- Reading addresses 0-29 and comparing ---");
        for (i = 0; i < 30; i = i + 1) begin
            read_word(i);
            if (data_in !== ref_mem[i])
                $display("   MISMATCH at addr %d: expected 0x%04X, got 0x%04X", i, ref_mem[i], data_in);
            else
                $display("  MATCH");
        end
  
  
        $display("\n--- Entering standby (CE = 1), trying write to address 0 ---");
        CE         = 1;  // standby
        OE         = 0;  // doesn't matter; CE=1 should dominate
        UB         = 0;
        LB         = 0;      
        WE         = 0;
        drive_data = 1;
        addr       = 0;
        data_out   = 16'hDEAD;
        #20;
        WE         = 1;  // back to read
        drive_data = 0;

        $display("\n--- Trying to read @0 in standby mode (expect zzzz) ---");
        CE         = 1;
        WE         = 1;
        OE         = 0;
        read_word_standby(0);

        $display("\n--- Leaving standby (CE = 0) and reading @0 again (expect original 0x%04h) ---", ref_mem[0]);
        CE = 0;
        OE = 0;
        WE = 1;
        read_word(0);

        $display("Expected original value: 0x%04h", ref_mem[0]);
        if (data_in === ref_mem[0])
            $display("   Correct: standby write was ignored (memory kept original value)");
        else
            $display("   Error: memory changed despite standby!");


        #5; // Small delay before finishing
        $display("\n--- Testbench complete ---");
        // $finish; // $finish is now uncommented to terminate the simulation
    end

endmodule

Homework/5/sram_waveform.vcd
$date
	Thu Jul 24 18:23:48 2025
$end
$version
	ModelSim Version 10.1d
$end
$timescale
	1ps
$end
$scope module tb_sram $end
$var reg 9 ! addr [8:0] $end
$var wire 1 " data [15] $end
$var wire 1 # data [14] $end
$var wire 1 $ data [13] $end
$var wire 1 % data [12] $end
$var wire 1 & data [11] $end
$var wire 1 ' data [10] $end
$var wire 1 ( data [9] $end
$var wire 1 ) data [8] $end
$var wire 1 * data [7] $end
$var wire 1 + data [6] $end
$var wire 1 , data [5] $end
$var wire 1 - data [4] $end
$var wire 1 . data [3] $end
$var wire 1 / data [2] $end
$var wire 1 0 data [1] $end
$var wire 1 1 data [0] $end
$var reg 1 2 CE $end
$var reg 1 3 OE $end
$var reg 1 4 WE $end
$var reg 1 5 UB $end
$var reg 1 6 LB $end
$var reg 16 7 data_out [15:0] $end
$var wire 1 8 data_in [15] $end
$var wire 1 9 data_in [14] $end
$var wire 1 : data_in [13] $end
$var wire 1 ; data_in [12] $end
$var wire 1 < data_in [11] $end
$var wire 1 = data_in [10] $end
$var wire 1 > data_in [9] $end
$var wire 1 ? data_in [8] $end
$var wire 1 @ data_in [7] $end
$var wire 1 A data_in [6] $end
$var wire 1 B data_in [5] $end
$var wire 1 C data_in [4] $end
$var wire 1 D data_in [3] $end
$var wire 1 E data_in [2] $end
$var wire 1 F data_in [1] $end
$var wire 1 G data_in [0] $end
$var reg 1 H drive_data $end
$var integer 32 I i $end
$scope task write_word $end
$var reg 9 J a [8:0] $end
$var reg 16 K d [15:0] $end
$upscope $end
$scope task read_word $end
$var reg 9 L a [8:0] $end
$upscope $end
$scope task read_word_standby $end
$var reg 9 M a [8:0] $end
$upscope $end
$scope module uut $end
$var parameter 32 N tRC $end
$var parameter 32 O tAA $end
$var parameter 32 P tOHA $end
$var parameter 32 Q tACE $end
$var parameter 32 R tDOE $end
$var parameter 32 S tHZOE $end
$var parameter 32 T tLZOE $end
$var parameter 32 U tHZCE $end
$var parameter 32 V tLZCE $end
$var parameter 32 W tBA $end
$var parameter 32 X tHZB $end
$var parameter 32 Y tLZB $end
$var parameter 32 Z tWC $end
$var parameter 32 [ tSCE $end
$var parameter 32 \ tAW $end
$var parameter 32 ] tHA $end
$var parameter 32 ^ tPWB $end
$var parameter 32 _ tPWE1 $end
$var parameter 32 ` tPWE2 $end
$var parameter 32 a tSD $end
$var parameter 32 b tHD $end
$var parameter 32 c tHZWE $end
$var parameter 32 d tLZWE $end
$var parameter 32 e tREAD $end
$var parameter 32 f tWRITE $end
$var wire 1 g addr [8] $end
$var wire 1 h addr [7] $end
$var wire 1 i addr [6] $end
$var wire 1 j addr [5] $end
$var wire 1 k addr [4] $end
$var wire 1 l addr [3] $end
$var wire 1 m addr [2] $end
$var wire 1 n addr [1] $end
$var wire 1 o addr [0] $end
$var wire 1 " data [15] $end
$var wire 1 # data [14] $end
$var wire 1 $ data [13] $end
$var wire 1 % data [12] $end
$var wire 1 & data [11] $end
$var wire 1 ' data [10] $end
$var wire 1 ( data [9] $end
$var wire 1 ) data [8] $end
$var wire 1 * data [7] $end
$var wire 1 + data [6] $end
$var wire 1 , data [5] $end
$var wire 1 - data [4] $end
$var wire 1 . data [3] $end
$var wire 1 / data [2] $end
$var wire 1 0 data [1] $end
$var wire 1 1 data [0] $end
$var wire 1 p CE $end
$var wire 1 q OE $end
$var wire 1 r WE $end
$var wire 1 s UB $end
$var wire 1 t LB $end
$var reg 16 u data_output [15:0] $end
$var wire 1 v CEx $end
$var wire 1 w OEx $end
$var wire 1 x WEx $end
$var wire 1 y UBx $end
$var wire 1 z LBx $end
$var wire 1 { ce_drv $end
$var wire 1 | oe_drv $end
$var wire 1 } we_drv $end
$var wire 1 ~ ub_drv $end
$var wire 1 !! lb_drv $end
$var wire 1 "! drive_bus $end
$var wire 1 #! read_raw $end
$var wire 1 $! write_raw $end
$upscope $end
$upscope $end
$enddefinitions $end
#0
$dumpvars
b0 !
02
03
04
05
06
b0 7
1H
bx u
b0 J
b0 K
bx L
bx M
b1010 N
b1010 O
b10 P
b1010 Q
b100 R
b100 S
b0 T
b100 U
b11 V
b100 W
b11 X
b0 Y
b1010 Z
b1000 [
b1000 \
b0 ]
b1000 ^
b1000 _
b1010 `
b110 a
b0 b
b101 c
b10 d
b1010 e
b1000 f
b0 I
x1
x0
x/
x.
x-
x,
x+
x*
x)
x(
x'
x&
x%
x$
x#
x"
xG
xF
xE
xD
xC
xB
xA
x@
x?
x>
x=
x<
x;
x:
x9
x8
1v
1w
1x
1y
1z
x{
1|
x}
1~
1!!
x"!
0#!
1$!
0t
0s
0r
0q
0p
0o
0n
0m
0l
0k
0j
0i
0h
0g
$end
#2000
1}
0"!
#3000
1{
#4000
01
00
0/
0.
0-
0,
0+
0*
0)
0(
0'
0&
0%
0$
0#
0"
0G
0F
0E
0D
0C
0B
0A
0@
0?
0>
0=
0<
0;
0:
09
08
#20000
14
0H
1r
0x
z1
z0
z/
z.
z-
z,
z+
z*
z)
z(
z'
z&
z%
z$
z#
z"
0$!
1#!
zG
zF
zE
zD
zC
zB
zA
z@
z?
z>
z=
z<
z;
z:
z9
z8
#25000
0}
1"!
x"
x#
x$
x%
x&
x'
x(
x)
x*
x+
x,
x-
x.
x/
x0
x1
xG
xF
xE
xD
xC
xB
xA
x@
x?
x>
x=
x<
x;
x:
x9
x8
b1 I
b1 J
b1 K
b1 !
b1 7
1H
04
0r
1x
1o
1$!
0#!
#27000
1}
0"!
#35000
11
00
0/
0.
0-
0,
0+
0*
0)
0(
0'
0&
0%
0$
0#
0"
1G
0F
0E
0D
0C
0B
0A
0@
0?
0>
0=
0<
0;
0:
09
08
#45000
14
0H
1r
0x
z1
z0
z/
z.
z-
z,
z+
z*
z)
z(
z'
z&
z%
z$
z#
z"
0$!
1#!
zG
zF
zE
zD
zC
zB
zA
z@
z?
z>
z=
z<
z;
z:
z9
z8
#50000
0}
1"!
x"
x#
x$
x%
x&
x'
x(
x)
x*
x+
x,
x-
x.
x/
x0
x1
xG
xF
xE
xD
xC
xB
xA
x@
x?
x>
x=
x<
x;
x:
x9
x8
b10 I
b10 J
b10 K
b10 !
b10 7
1H
04
0r
1x
0o
1n
1$!
0#!
#52000
1}
0"!
#60000
01
10
0/
0.
0-
0,
0+
0*
0)
0(
0'
0&
0%
0$
0#
0"
0G
1F
0E
0D
0C
0B
0A
0@
0?
0>
0=
0<
0;
0:
09
08
#70000
14
0H
1r
0x
z1
z0
z/
z.
z-
z,
z+
z*
z)
z(
z'
z&
z%
z$
z#
z"
0$!
1#!
zG
zF
zE
zD
zC
zB
zA
z@
z?
z>
z=
z<
z;
z:
z9
z8
#75000
0}
1"!
x"
x#
x$
x%
x&
x'
x(
x)
x*
x+
x,
x-
x.
x/
x0
x1
xG
xF
xE
xD
xC
xB
xA
x@
x?
x>
x=
x<
x;
x:
x9
x8
b11 I
b11 J
b11 K
b11 !
b11 7
1H
04
0r
1x
1o
1$!
0#!
#77000
1}
0"!
#85000
11
10
0/
0.
0-
0,
0+
0*
0)
0(
0'
0&
0%
0$
0#
0"
1G
1F
0E
0D
0C
0B
0A
0@
0?
0>
0=
0<
0;
0:
09
08
#95000
14
0H
1r
0x
z1
z0
z/
z.
z-
z,
z+
z*
z)
z(
z'
z&
z%
z$
z#
z"
0$!
1#!
zG
zF
zE
zD
zC
zB
zA
z@
z?
z>
z=
z<
z;
z:
z9
z8
#100000
0}
1"!
x"
x#
x$
x%
x&
x'
x(
x)
x*
x+
x,
x-
x.
x/
x0
x1
xG
xF
xE
xD
xC
xB
xA
x@
x?
x>
x=
x<
x;
x:
x9
x8
b100 I
b100 J
b100 K
b100 !
b100 7
1H
04
0r
1x
0o
0n
1m
1$!
0#!
#102000
1}
0"!
#110000
01
00
1/
0.
0-
0,
0+
0*
0)
0(
0'
0&
0%
0$
0#
0"
0G
0F
1E
0D
0C
0B
0A
0@
0?
0>
0=
0<
0;
0:
09
08
#120000
14
0H
1r
0x
z1
z0
z/
z.
z-
z,
z+
z*
z)
z(
z'
z&
z%
z$
z#
z"
0$!
1#!
zG
zF
zE
zD
zC
zB
zA
z@
z?
z>
z=
z<
z;
z:
z9
z8
#125000
0}
1"!
x"
x#
x$
x%
x&
x'
x(
x)
x*
x+
x,
x-
x.
x/
x0
x1
xG
xF
xE
xD
xC
xB
xA
x@
x?
x>
x=
x<
x;
x:
x9
x8
b101 I
b101 J
b101 K
b101 !
b101 7
1H
04
0r
1x
1o
1$!
0#!
#127000
1}
0"!
#135000
11
00
1/
0.
0-
0,
0+
0*
0)
0(
0'
0&
0%
0$
0#
0"
1G
0F
1E
0D
0C
0B
0A
0@
0?
0>
0=
0<
0;
0:
09
08
#145000
14
0H
1r
0x
z1
z0
z/
z.
z-
z,
z+
z*
z)
z(
z'
z&
z%
z$
z#
z"
0$!
1#!
zG
zF
zE
zD
zC
zB
zA
z@
z?
z>
z=
z<
z;
z:
z9
z8
#150000
0}
1"!
x"
x#
x$
x%
x&
x'
x(
x)
x*
x+
x,
x-
x.
x/
x0
x1
xG
xF
xE
xD
xC
xB
xA
x@
x?
x>
x=
x<
x;
x:
x9
x8
b110 I
b110 J
b110 K
b110 !
b110 7
1H
04
0r
1x
0o
1n
1$!
0#!
#152000
1}
0"!
#160000
01
10
1/
0.
0-
0,
0+
0*
0)
0(
0'
0&
0%
0$
0#
0"
0G
1F
1E
0D
0C
0B
0A
0@
0?
0>
0=
0<
0;
0:
09
08
#170000
14
0H
1r
0x
z1
z0
z/
z.
z-
z,
z+
z*
z)
z(
z'
z&
z%
z$
z#
z"
0$!
1#!
zG
zF
zE
zD
zC
zB
zA
z@
z?
z>
z=
z<
z;
z:
z9
z8
#175000
0}
1"!
x"
x#
x$
x%
x&
x'
x(
x)
x*
x+
x,
x-
x.
x/
x0
x1
xG
xF
xE
xD
xC
xB
xA
x@
x?
x>
x=
x<
x;
x:
x9
x8
b111 I
b111 J
b111 K
b111 !
b111 7
1H
04
0r
1x
1o
1$!
0#!
#177000
1}
0"!
#185000
11
10
1/
0.
0-
0,
0+
0*
0)
0(
0'
0&
0%
0$
0#
0"
1G
1F
1E
0D
0C
0B
0A
0@
0?
0>
0=
0<
0;
0:
09
08
#195000
14
0H
1r
0x
z1
z0
z/
z.
z-
z,
z+
z*
z)
z(
z'
z&
z%
z$
z#
z"
0$!
1#!
zG
zF
zE
zD
zC
zB
zA
z@
z?
z>
z=
z<
z;
z:
z9
z8
#200000
0}
1"!
x"
x#
x$
x%
x&
x'
x(
x)
x*
x+
x,
x-
x.
x/
x0
x1
xG
xF
xE
xD
xC
xB
xA
x@
x?
x>
x=
x<
x;
x:
x9
x8
b1000 I
b1000 J
b1000 K
b1000 !
b1000 7
1H
04
0r
1x
0o
0n
0m
1l
1$!
0#!
#202000
1}
0"!
#210000
01
00
0/
1.
0-
0,
0+
0*
0)
0(
0'
0&
0%
0$
0#
0"
0G
0F
0E
1D
0C
0B
0A
0@
0?
0>
0=
0<
0;
0:
09
08
#220000
14
0H
1r
0x
z1
z0
z/
z.
z-
z,
z+
z*
z)
z(
z'
z&
z%
z$
z#
z"
0$!
1#!
zG
zF
zE
zD
zC
zB
zA
z@
z?
z>
z=
z<
z;
z:
z9
z8
#225000
0}
1"!
x"
x#
x$
x%
x&
x'
x(
x)
x*
x+
x,
x-
x.
x/
x0
x1
xG
xF
xE
xD
xC
xB
xA
x@
x?
x>
x=
x<
x;
x:
x9
x8
b1001 I
b1001 J
b1001 K
b1001 !
b1001 7
1H
04
0r
1x
1o
1$!
0#!
#227000
1}
0"!
#235000
11
00
0/
1.
0-
0,
0+
0*
0)
0(
0'
0&
0%
0$
0#
0"
1G
0F
0E
1D
0C
0B
0A
0@
0?
0>
0=
0<
0;
0:
09
08
#245000
14
0H
1r
0x
z1
z0
z/
z.
z-
z,
z+
z*
z)
z(
z'
z&
z%
z$
z#
z"
0$!
1#!
zG
zF
zE
zD
zC
zB
zA
z@
z?
z>
z=
z<
z;
z:
z9
z8
#250000
0}
1"!
x"
x#
x$
x%
x&
x'
x(
x)
x*
x+
x,
x-
x.
x/
x0
x1
xG
xF
xE
xD
xC
xB
xA
x@
x?
x>
x=
x<
x;
x:
x9
x8
b1010 I
b1010 J
b10000000000 K
b1010 !
b10000000000 7
1H
04
0r
1x
0o
1n
1$!
0#!
#252000
1}
0"!
#260000
01
00
0/
0.
0-
0,
0+
0*
0)
0(
1'
0&
0%
0$
0#
0"
0G
0F
0E
0D
0C
0B
0A
0@
0?
0>
1=
0<
0;
0:
09
08
#270000
14
0H
1r
0x
z1
z0
z/
z.
z-
z,
z+
z*
z)
z(
z'
z&
z%
z$
z#
z"
0$!
1#!
zG
zF
zE
zD
zC
zB
zA
z@
z?
z>
z=
z<
z;
z:
z9
z8
#275000
0}
1"!
x"
x#
x$
x%
x&
x'
x(
x)
x*
x+
x,
x-
x.
x/
x0
x1
xG
xF
xE
xD
xC
xB
xA
x@
x?
x>
x=
x<
x;
x:
x9
x8
b1011 I
b1011 J
b1011 !
1H
04
0r
1x
1o
1$!
0#!
#277000
1}
0"!
#285000
01
00
0/
0.
0-
0,
0+
0*
0)
0(
1'
0&
0%
0$
0#
0"
0G
0F
0E
0D
0C
0B
0A
0@
0?
0>
1=
0<
0;
0:
09
08
#295000
14
0H
1r
0x
z1
z0
z/
z.
z-
z,
z+
z*
z)
z(
z'
z&
z%
z$
z#
z"
0$!
1#!
zG
zF
zE
zD
zC
zB
zA
z@
z?
z>
z=
z<
z;
z:
z9
z8
#300000
0}
1"!
x"
x#
x$
x%
x&
x'
x(
x)
x*
x+
x,
x-
x.
x/
x0
x1
xG
xF
xE
xD
xC
xB
xA
x@
x?
x>
x=
x<
x;
x:
x9
x8
b1100 I
b1100 J
b1100 !
1H
04
0r
1x
0o
0n
1m
1$!
0#!
#302000
1}
0"!
#310000
01
00
0/
0.
0-
0,
0+
0*
0)
0(
1'
0&
0%
0$
0#
0"
0G
0F
0E
0D
0C
0B
0A
0@
0?
0>
1=
0<
0;
0:
09
08
#320000
14
0H
1r
0x
z1
z0
z/
z.
z-
z,
z+
z*
z)
z(
z'
z&
z%
z$
z#
z"
0$!
1#!
zG
zF
zE
zD
zC
zB
zA
z@
z?
z>
z=
z<
z;
z:
z9
z8
#325000
0}
1"!
x"
x#
x$
x%
x&
x'
x(
x)
x*
x+
x,
x-
x.
x/
x0
x1
xG
xF
xE
xD
xC
xB
xA
x@
x?
x>
x=
x<
x;
x:
x9
x8
b1101 I
b1101 J
b1101 !
1H
04
0r
1x
1o
1$!
0#!
#327000
1}
0"!
#335000
01
00
0/
0.
0-
0,
0+
0*
0)
0(
1'
0&
0%
0$
0#
0"
0G
0F
0E
0D
0C
0B
0A
0@
0?
0>
1=
0<
0;
0:
09
08
#345000
14
0H
1r
0x
z1
z0
z/
z.
z-
z,
z+
z*
z)
z(
z'
z&
z%
z$
z#
z"
0$!
1#!
zG
zF
zE
zD
zC
zB
zA
z@
z?
z>
z=
z<
z;
z:
z9
z8
#350000
0}
1"!
x"
x#
x$
x%
x&
x'
x(
x)
x*
x+
x,
x-
x.
x/
x0
x1
xG
xF
xE
xD
xC
xB
xA
x@
x?
x>
x=
x<
x;
x:
x9
x8
b1110 I
b1110 J
b1110 !
1H
04
0r
1x
0o
1n
1$!
0#!
#352000
1}
0"!
#360000
01
00
0/
0.
0-
0,
0+
0*
0)
0(
1'
0&
0%
0$
0#
0"
0G
0F
0E
0D
0C
0B
0A
0@
0?
0>
1=
0<
0;
0:
09
08
#370000
14
0H
1r
0x
z1
z0
z/
z.
z-
z,
z+
z*
z)
z(
z'
z&
z%
z$
z#
z"
0$!
1#!
zG
zF
zE
zD
zC
zB
zA
z@
z?
z>
z=
z<
z;
z:
z9
z8
#375000
0}
1"!
x"
x#
x$
x%
x&
x'
x(
x)
x*
x+
x,
x-
x.
x/
x0
x1
xG
xF
xE
xD
xC
xB
xA
x@
x?
x>
x=
x<
x;
x:
x9
x8
b1111 I
b1111 J
b1111 !
1H
04
0r
1x
1o
1$!
0#!
#377000
1}
0"!
#385000
01
00
0/
0.
0-
0,
0+
0*
0)
0(
1'
0&
0%
0$
0#
0"
0G
0F
0E
0D
0C
0B
0A
0@
0?
0>
1=
0<
0;
0:
09
08
#395000
14
0H
1r
0x
z1
z0
z/
z.
z-
z,
z+
z*
z)
z(
z'
z&
z%
z$
z#
z"
0$!
1#!
zG
zF
zE
zD
zC
zB
zA
z@
z?
z>
z=
z<
z;
z:
z9
z8
#400000
0}
1"!
x"
x#
x$
x%
x&
x'
x(
x)
x*
x+
x,
x-
x.
x/
x0
x1
xG
xF
xE
xD
xC
xB
xA
x@
x?
x>
x=
x<
x;
x:
x9
x8
b10000 I
b10000 J
b10000 !
1H
04
0r
1x
0o
0n
0m
0l
1k
1$!
0#!
#402000
1}
0"!
#410000
01
00
0/
0.
0-
0,
0+
0*
0)
0(
1'
0&
0%
0$
0#
0"
0G
0F
0E
0D
0C
0B
0A
0@
0?
0>
1=
0<
0;
0:
09
08
#420000
14
0H
1r
0x
z1
z0
z/
z.
z-
z,
z+
z*
z)
z(
z'
z&
z%
z$
z#
z"
0$!
1#!
zG
zF
zE
zD
zC
zB
zA
z@
z?
z>
z=
z<
z;
z:
z9
z8
#425000
0}
1"!
x"
x#
x$
x%
x&
x'
x(
x)
x*
x+
x,
x-
x.
x/
x0
x1
xG
xF
xE
xD
xC
xB
xA
x@
x?
x>
x=
x<
x;
x:
x9
x8
b10001 I
b10001 J
b10100000000 K
b10001 !
b10100000000 7
1H
04
0r
1x
1o
1$!
0#!
#427000
1}
0"!
#435000
01
00
0/
0.
0-
0,
0+
0*
1)
0(
1'
0&
0%
0$
0#
0"
0G
0F
0E
0D
0C
0B
0A
0@
1?
0>
1=
0<
0;
0:
09
08
#445000
14
0H
1r
0x
z1
z0
z/
z.
z-
z,
z+
z*
z)
z(
z'
z&
z%
z$
z#
z"
0$!
1#!
zG
zF
zE
zD
zC
zB
zA
z@
z?
z>
z=
z<
z;
z:
z9
z8
#450000
0}
1"!
x"
x#
x$
x%
x&
x'
x(
x)
x*
x+
x,
x-
x.
x/
x0
x1
xG
xF
xE
xD
xC
xB
xA
x@
x?
x>
x=
x<
x;
x:
x9
x8
b10010 I
b10010 J
b10010 !
1H
04
0r
1x
0o
1n
1$!
0#!
#452000
1}
0"!
#460000
01
00
0/
0.
0-
0,
0+
0*
1)
0(
1'
0&
0%
0$
0#
0"
0G
0F
0E
0D
0C
0B
0A
0@
1?
0>
1=
0<
0;
0:
09
08
#470000
14
0H
1r
0x
z1
z0
z/
z.
z-
z,
z+
z*
z)
z(
z'
z&
z%
z$
z#
z"
0$!
1#!
zG
zF
zE
zD
zC
zB
zA
z@
z?
z>
z=
z<
z;
z:
z9
z8
#475000
0}
1"!
x"
x#
x$
x%
x&
x'
x(
x)
x*
x+
x,
x-
x.
x/
x0
x1
xG
xF
xE
xD
xC
xB
xA
x@
x?
x>
x=
x<
x;
x:
x9
x8
b10011 I
b10011 J
b10011 !
1H
04
0r
1x
1o
1$!
0#!
#477000
1}
0"!
#485000
01
00
0/
0.
0-
0,
0+
0*
1)
0(
1'
0&
0%
0$
0#
0"
0G
0F
0E
0D
0C
0B
0A
0@
1?
0>
1=
0<
0;
0:
09
08
#495000
14
0H
1r
0x
z1
z0
z/
z.
z-
z,
z+
z*
z)
z(
z'
z&
z%
z$
z#
z"
0$!
1#!
zG
zF
zE
zD
zC
zB
zA
z@
z?
z>
z=
z<
z;
z:
z9
z8
#500000
0}
1"!
x"
x#
x$
x%
x&
x'
x(
x)
x*
x+
x,
x-
x.
x/
x0
x1
xG
xF
xE
xD
xC
xB
xA
x@
x?
x>
x=
x<
x;
x:
x9
x8
b10100 I
b10100 J
b11010100100100 K
b10100 !
b11010100100100 7
1H
04
0r
1x
0o
0n
1m
1$!
0#!
#502000
1}
0"!
#510000
01
00
1/
0.
0-
1,
0+
0*
1)
0(
1'
0&
1%
1$
0#
0"
0G
0F
1E
0D
0C
1B
0A
0@
1?
0>
1=
0<
1;
1:
09
08
#520000
14
0H
1r
0x
z1
z0
z/
z.
z-
z,
z+
z*
z)
z(
z'
z&
z%
z$
z#
z"
0$!
1#!
zG
zF
zE
zD
zC
zB
zA
z@
z?
z>
z=
z<
z;
z:
z9
z8
#525000
0}
1"!
x"
x#
x$
x%
x&
x'
x(
x)
x*
x+
x,
x-
x.
x/
x0
x1
xG
xF
xE
xD
xC
xB
xA
x@
x?
x>
x=
x<
x;
x:
x9
x8
b10101 I
b10101 J
b101111010000001 K
b10101 !
b101111010000001 7
1H
04
0r
1x
1o
1$!
0#!
#527000
1}
0"!
#535000
11
00
0/
0.
0-
0,
0+
1*
0)
1(
1'
1&
1%
0$
1#
0"
1G
0F
0E
0D
0C
0B
0A
1@
0?
1>
1=
1<
1;
0:
19
08
#545000
14
0H
1r
0x
z1
z0
z/
z.
z-
z,
z+
z*
z)
z(
z'
z&
z%
z$
z#
z"
0$!
1#!
zG
zF
zE
zD
zC
zB
zA
z@
z?
z>
z=
z<
z;
z:
z9
z8
#550000
0}
1"!
x"
x#
x$
x%
x&
x'
x(
x)
x*
x+
x,
x-
x.
x/
x0
x1
xG
xF
xE
xD
xC
xB
xA
x@
x?
x>
x=
x<
x;
x:
x9
x8
b10110 I
b10110 J
b1101011000001001 K
b10110 !
b1101011000001001 7
1H
04
0r
1x
0o
1n
1$!
0#!
#552000
1}
0"!
#560000
11
00
0/
1.
0-
0,
0+
0*
0)
1(
1'
0&
1%
0$
1#
1"
1G
0F
0E
1D
0C
0B
0A
0@
0?
1>
1=
0<
1;
0:
19
18
