Homework/3/top.v
`timescale 1ns/1ns
module HalfAdder(input A, B, output Sum, Carry);
    xor #2 (Sum, A, B);     // Sum with 2ns delay
    and #3 (Carry, A, B);   // Carry with 3ns delay
endmodule

`timescale 1ns/1ns
module FullAdder(input A, B, Cin, output S, Cout);
    wire sum1, carry1, carry2;
    HalfAdder HA1(.A(A), .B(B), .Sum(sum1), .Carry(carry1));
    HalfAdder HA2(.A(sum1), .B(Cin), .Sum(S), .Carry(carry2));
    or #0 (Cout, carry1, carry2);// OR gate with 0ns delay
endmodule


module adder(input cin, input [3:0] a, b, output cout, output [3:0] s);
    wire [2:0] carry;
    FullAdder FA0(.A(a[0]), .B(b[0]), .Cin(cin), .S(s[0]), .Cout(carry[0]));
    FullAdder FA1(.A(a[1]), .B(b[1]), .Cin(carry[0]), .S(s[1]), .Cout(carry[1]));
    FullAdder FA2(.A(a[2]), .B(b[2]), .Cin(carry[1]), .S(s[2]), .Cout(carry[2]));
    FullAdder FA3(.A(a[3]), .B(b[3]), .Cin(carry[2]), .S(s[3]), .Cout(cout));
endmodule



`timescale 1ns/1ns
module test_bench();

    reg [3:0] A, B;
    reg Cin;
    wire [3:0] Sum;
    wire Cout;

    reg [4:0] expected_result;
    integer total_tests = 0;
    integer successful_tests = 0;
    realtime max_delay = 0;
    realtime start_time, end_time;

    integer i, j; // Declare loop variables

    adder uut(.a(A), .b(B), .cin(Cin), .s(Sum), .cout(Cout));

    task check_result;
        input [3:0] a_val, b_val;
        input cin_val;
        reg [4:0] local_expected;
        realtime local_start, local_end;
        reg timeout_flag;
        begin
            A = a_val;
            B = b_val;
            Cin = cin_val;
            local_expected = A + B + Cin;
            timeout_flag = 0;
            local_start = $realtime;

            fork
                begin
                    wait({Cout, Sum} === local_expected);
                    local_end = $realtime;
                end

                begin
                    #50;
                    if ({Cout, Sum} !== local_expected) begin
                        $display("Warning: Timeout at %0tns for A=%b, B=%b, Cin=%b", $time, A, B, Cin);
                        timeout_flag = 1;
                        local_end = $realtime;
                    end
                end
            join

            if ((local_end - local_start) > max_delay)
                max_delay = local_end - local_start;

            total_tests = total_tests + 1;

            if (!timeout_flag && ({Cout, Sum} === local_expected)) begin
                successful_tests = successful_tests + 1;
                $display("PASS: A=%b, B=%b, Cin=%b => Sum=%b, Cout=%b (Delay: %0tns)",
                         A, B, Cin, Sum, Cout, local_end - local_start);
            end else begin
                $display("FAIL: A=%b, B=%b, Cin=%b => Got {Cout=%b, Sum=%b}, Expected {Cout=%b, Sum=%b}",
                         A, B, Cin, Cout, Sum, local_expected[4], local_expected[3:0]);
            end
        end
    endtask

    initial begin
        #10;
        for (i = 0; i < 16; i = i + 1) begin
            for (j = 0; j < 16; j = j + 1) begin
                check_result(i[3:0], j[3:0], 1'b1);
                check_result(i[3:0], j[3:0], 1'b0);
            end
        end

        $display("\nTest Results:");
        $display("Successful calculations: %0d / %0d", successful_tests, total_tests);
        $display("Maximum delay observed: %0.3f ns", max_delay);
        $display("Theoretical worst-case delay: 14 ns");

        $finish;
    end
endmodule

Homework/3/simulation.vcd
$date
	Fri May 02 19:24:35 2025
$end
$version
	ModelSim Version 10.1d
$end
$timescale
	1ns
$end
$scope module test_bench $end
$var reg 4 ! A [3:0] $end
$var reg 4 " B [3:0] $end
$var reg 1 # Cin $end
$var wire 1 $ Sum [3] $end
$var wire 1 % Sum [2] $end
$var wire 1 & Sum [1] $end
$var wire 1 ' Sum [0] $end
$var wire 1 ( Cout $end
$var reg 5 ) expected_result [4:0] $end
$var integer 32 * total_tests $end
$var integer 32 + successful_tests $end
$var real 0 , max_delay $end
$var real 0 - start_time $end
$var real 0 . end_time $end
$var integer 32 / i $end
$var integer 32 0 j $end
$scope task check_result $end
$var reg 4 1 a_val [3:0] $end
$var reg 4 2 b_val [3:0] $end
$var reg 1 3 cin_val $end
$var reg 5 4 local_expected [4:0] $end
$var real 0 5 local_start $end
$var real 0 6 local_end $end
$var reg 1 7 timeout_flag $end
$upscope $end
$scope module uut $end
$var wire 1 8 cin $end
$var wire 1 9 a [3] $end
$var wire 1 : a [2] $end
$var wire 1 ; a [1] $end
$var wire 1 < a [0] $end
$var wire 1 = b [3] $end
$var wire 1 > b [2] $end
$var wire 1 ? b [1] $end
$var wire 1 @ b [0] $end
$var wire 1 ( cout $end
$var wire 1 $ s [3] $end
$var wire 1 % s [2] $end
$var wire 1 & s [1] $end
$var wire 1 ' s [0] $end
$var wire 1 A carry [2] $end
$var wire 1 B carry [1] $end
$var wire 1 C carry [0] $end
$scope module FA0 $end
$var wire 1 < A $end
$var wire 1 @ B $end
$var wire 1 8 Cin $end
$var wire 1 ' S $end
$var wire 1 C Cout $end
$var wire 1 D sum1 $end
$var wire 1 E carry1 $end
$var wire 1 F carry2 $end
$scope module HA1 $end
$var wire 1 < A $end
$var wire 1 @ B $end
$var wire 1 D Sum $end
$var wire 1 E Carry $end
$upscope $end
$scope module HA2 $end
$var wire 1 D A $end
$var wire 1 8 B $end
$var wire 1 ' Sum $end
$var wire 1 F Carry $end
$upscope $end
$upscope $end
$scope module FA1 $end
$var wire 1 ; A $end
$var wire 1 ? B $end
$var wire 1 C Cin $end
$var wire 1 & S $end
$var wire 1 B Cout $end
$var wire 1 G sum1 $end
$var wire 1 H carry1 $end
$var wire 1 I carry2 $end
$scope module HA1 $end
$var wire 1 ; A $end
$var wire 1 ? B $end
$var wire 1 G Sum $end
$var wire 1 H Carry $end
$upscope $end
$scope module HA2 $end
$var wire 1 G A $end
$var wire 1 C B $end
$var wire 1 & Sum $end
$var wire 1 I Carry $end
$upscope $end
$upscope $end
$scope module FA2 $end
$var wire 1 : A $end
$var wire 1 > B $end
$var wire 1 B Cin $end
$var wire 1 % S $end
$var wire 1 A Cout $end
$var wire 1 J sum1 $end
$var wire 1 K carry1 $end
$var wire 1 L carry2 $end
$scope module HA1 $end
$var wire 1 : A $end
$var wire 1 > B $end
$var wire 1 J Sum $end
$var wire 1 K Carry $end
$upscope $end
$scope module HA2 $end
$var wire 1 J A $end
$var wire 1 B B $end
$var wire 1 % Sum $end
$var wire 1 L Carry $end
$upscope $end
$upscope $end
$scope module FA3 $end
$var wire 1 9 A $end
$var wire 1 = B $end
$var wire 1 A Cin $end
$var wire 1 $ S $end
$var wire 1 ( Cout $end
$var wire 1 M sum1 $end
$var wire 1 N carry1 $end
$var wire 1 O carry2 $end
$scope module HA1 $end
$var wire 1 9 A $end
$var wire 1 = B $end
$var wire 1 M Sum $end
$var wire 1 N Carry $end
$upscope $end
$scope module HA2 $end
$var wire 1 M A $end
$var wire 1 A B $end
$var wire 1 $ Sum $end
$var wire 1 O Carry $end
$upscope $end
$upscope $end
$upscope $end
$upscope $end
$enddefinitions $end
#0
$dumpvars
bx !
bx "
x#
bx )
bx 1
bx 2
x3
bx 4
x7
b0 *
b0 +
bx /
bx 0
r0 ,
r0 -
r0 .
r0 5
r0 6
x'
x&
x%
x$
x(
xC
xB
xA
xD
xE
xF
xG
xH
xI
xJ
xK
xL
xM
xN
xO
x8
x@
x?
x>
x=
x<
x;
x:
x9
$end
#10
b0 /
b0 0
b0 1
b0 2
13
b0 !
b0 "
1#
b1 4
07
r10 5
0@
0?
0>
0=
0<
0;
0:
09
18
#12
0D
0G
0J
0M
#13
0E
0H
0K
0N
#14
1'
#15
0F
0I
0L
0O
0C
0B
0A
0(
#17
0&
0%
0$
r17 6
#60
r7 ,
b1 *
b1 +
03
0#
b0 4
r60 5
08
#62
0'
r62 6
#110
b10 *
b10 +
b1 0
b1 2
13
b1 "
1#
b10 4
r110 5
1@
18
#112
1D
1'
#114
0'
#115
1F
1C
#117
1&
r117 6
#160
b11 *
b11 +
03
0#
b1 4
r160 5
08
#162
1'
#163
0F
0C
#165
0&
r165 6
#210
b100 *
b100 +
b10 0
b10 2
13
b10 "
1#
b11 4
r210 5
0@
1?
18
#212
0D
1G
0'
#214
1'
1&
r214 6
#260
b101 *
b101 +
03
0#
b10 4
r260 5
08
#262
0'
r262 6
#310
b110 *
b110 +
b11 0
b11 2
13
b11 "
1#
b100 4
r310 5
1@
18
#312
1D
1'
#314
0'
#315
1F
1C
#317
0&
#318
1I
1B
#320
1%
r320 6
#360
r10 ,
b111 *
b111 +
03
0#
b11 4
r360 5
08
#362
1'
#363
0F
0C
#365
1&
#366
0I
0B
#368
0%
r368 6
#410
b1000 *
b1000 +
b100 0
b100 2
13
b100 "
1#
b101 4
r410 5
0@
0?
1>
18
#412
0D
0G
1J
0'
#414
1'
0&
1%
r414 6
#460
b1001 *
b1001 +
03
0#
b100 4
r460 5
08
#462
0'
r462 6
#510
b1010 *
b1010 +
b101 0
b101 2
13
b101 "
1#
b110 4
r510 5
1@
18
#512
1D
1'
#514
0'
#515
1F
1C
#517
1&
r517 6
#560
b1011 *
b1011 +
03
0#
b101 4
r560 5
08
#562
1'
#563
0F
0C
#565
0&
r565 6
#610
b1100 *
b1100 +
b110 0
b110 2
13
b110 "
1#
b111 4
r610 5
0@
1?
18
#612
0D
1G
0'
#614
1'
1&
r614 6
#660
b1101 *
b1101 +
03
0#
b110 4
r660 5
08
#662
0'
r662 6
#710
b1110 *
b1110 +
b111 0
b111 2
13
b111 "
1#
b1000 4
r710 5
1@
18
#712
1D
1'
#714
0'
#715
1F
1C
#717
0&
#718
1I
1B
#720
0%
#721
1L
1A
#723
1$
r723 6
#760
r13 ,
b1111 *
b1111 +
03
0#
b111 4
r760 5
08
#762
1'
#763
0F
0C
#765
1&
#766
0I
0B
#768
1%
#769
0L
0A
#771
0$
r771 6
#810
b10000 *
b10000 +
b1000 0
b1000 2
13
b1000 "
1#
b1001 4
r810 5
0@
0?
0>
1=
18
#812
0D
0G
0J
1M
0'
#814
1'
0&
0%
1$
r814 6
#860
b10001 *
b10001 +
03
0#
b1000 4
r860 5
08
#862
0'
r862 6
#910
b10010 *
b10010 +
b1001 0
b1001 2
13
b1001 "
1#
b1010 4
r910 5
1@
18
#912
1D
1'
#914
0'
#915
1F
1C
#917
1&
r917 6
#960
b10011 *
b10011 +
03
0#
b1001 4
r960 5
08
#962
1'
#963
0F
0C
#965
0&
r965 6
#1010
b10100 *
b10100 +
b1010 0
b1010 2
13
b1010 "
1#
b1011 4
r1010 5
0@
1?
18
#1012
0D
1G
0'
#1014
1'
1&
r1014 6
#1060
b10101 *
b10101 +
03
0#
b1010 4
r1060 5
08
#1062
0'
r1062 6
#1110
b10110 *
b10110 +
b1011 0
b1011 2
13
b1011 "
1#
b1100 4
r1110 5
1@
18
#1112
1D
1'
#1114
0'
#1115
1F
1C
#1117
0&
#1118
1I
1B
#1120
1%
r1120 6
#1160
b10111 *
b10111 +
03
0#
b1011 4
r1160 5
08
#1162
1'
#1163
0F
0C
#1165
1&
#1166
0I
0B
#1168
0%
r1168 6
#1210
b11000 *
b11000 +
b1100 0
b1100 2
13
b1100 "
1#
b1101 4
r1210 5
0@
0?
1>
18
#1212
0D
0G
1J
0'
#1214
1'
0&
1%
r1214 6
#1260
b11001 *
b11001 +
03
0#
b1100 4
r1260 5
08
#1262
0'
r1262 6
#1310
b11010 *
b11010 +
b1101 0
b1101 2
13
b1101 "
1#
b1110 4
r1310 5
1@
18
#1312
1D
1'
#1314
0'
#1315
1F
1C
#1317
1&
r1317 6
#1360
b11011 *
b11011 +
03
0#
b1101 4
r1360 5
08
#1362
1'
#1363
0F
0C
#1365
0&
r1365 6
#1410
b11100 *
b11100 +
b1110 0
b1110 2
13
b1110 "
1#
b1111 4
r1410 5
0@
1?
18
#1412
0D
1G
0'
#1414
1'
1&
r1414 6
#1460
b11101 *
b11101 +
03
0#
b1110 4
r1460 5
08
#1462
0'
r1462 6
#1510
b11110 *
b11110 +
b1111 0
b1111 2
13
b1111 "
1#
b10000 4
r1510 5
1@
18
#1512
1D
1'
#1514
0'
#1515
1F
1C
#1517
0&
#1518
1I
1B
#1520
0%
#1521
1L
1A
#1523
0$
#1524
1O
1(
r1524 6
#1560
r14 ,
b11111 *
b11111 +
03
0#
b1111 4
r1560 5
08
#1562
1'
#1563
0F
0C
#1565
1&
#1566
0I
0B
#1568
1%
#1569
0L
0A
#1571
1$
#1572
0O
0(
r1572 6
#1610
b100000 *
b100000 +
b10000 0
b1 /
b0 0
b1 1
b0 2
13
b1 !
b0 "
1#
b10 4
r1610 5
0@
0?
0>
0=
1<
18
#1612
0G
0J
0M
0'
#1613
1F
1C
#1614
0%
0$
r1614 6
#1660
b100001 *
b100001 +
03
0#
b1 4
r1660 5
08
#1662
1'
#1663
0F
0C
#1665
0&
r1665 6
#1710
b100010 *
b100010 +
b1 0
b1 2
13
b1 "
1#
b11 4
r1710 5
1@
18
#1712
0D
0'
#1713
1E
1C
#1714
1'
#1715
1&
r1715 6
#1760
b100011 *
b100011 +
03
0#
b10 4
r1760 5
08
#1762
0'
r1762 6
#1810
b100100 *
b100100 +
b10 0
b10 2
13
b10 "
1#
b100 4
r1810 5
0@
1?
18
#1812
1D
1G
1'
#1813
0E
0C
#1814
0'
#1815
1F
1C
#1817
0&
#1818
1I
1B
#1820
1%
r1820 6
#1860
b100101 *
b100101 +
03
0#
b11 4
r1860 5
08
#1862
1'
#1863
0F
0C
#1865
1&
#1866
0I
0B
#1868
0%
r1868 6
#1910
b100110 *
b100110 +
b11 0
b11 2
13
b11 "
1#
b101 4
r1910 5
1@
18
#1912
0D
0'
#1913
1E
1C
#1914
1'
#1915
0&
#1916
1I
1B
#1918
1%
r1918 6
#1960
b100111 *
b100111 +
03
0#
b100 4
r1960 5
08
#1962
0'
r1962 6
#2010
b101000 *
b101000 +
b100 0
b100 2
13
b100 "
1#
b110 4
r2010 5
0@
0?
1>
18
#2012
1D
0G
1J
1'
#2013
0E
0C
#2014
0'
0%
#2015
1F
0I
1L
1C
0B
1A
#2017
1&
1%
1$
#2018
0L
0A
#2020
0$
r2020 6
#2060
b101001 *
b101001 +
03
0#
b101 4
r2060 5
08
#2062
1'
#2063
0F
0C
#2065
0&
r2065 6
#2110
b101010 *
b101010 +
b101 0
b101 2
13
b101 "
1#
b111 4
r2110 5
1@
18
#2112
0D
0'
#2113
1E
1C
#2114
1'
#2115
1&
r2115 6
#2160
b101011 *
b101011 +
03
0#
b110 4
r2160 5
08
#2162
0'
r2162 6
#2210
b101100 *
b101100 +
b110 0
b110 2
13
b110 "
1#
b1000 4
r2210 5
0@
1?
18
#2212
1D
1G
1'
#2213
0E
0C
#2214
0'
#2215
1F
1C
#2217
0&
#2218
1I
1B
#2220
0%
#2221
1L
1A
#2223
1$
r2223 6
#2260
b101101 *
b101101 +
03
0#
b111 4
r2260 5
08
#2262
1'
#2263
0F
0C
#2265
1&
#2266
0I
0B
#2268
1%
#2269
0L
0A
#2271
0$
r2271 6
#2310
b101110 *
b101110 +
b111 0
b111 2
13
b111 "
1#
b1001 4
r2310 5
1@
18
#2312
0D
0'
#2313
1E
1C
#2314
1'
#2315
0&
#2316
1I
1B
#2318
0%
#2319
1L
1A
#2321
1$
r2321 6
#2360
b101111 *
b101111 +
03
0#
b1000 4
r2360 5
08
#2362
0'
r2362 6
#2410
b110000 *
b110000 +
b1000 0
b1000 2
13
b1000 "
1#
b1010 4
r2410 5
0@
0?
0>
1=
18
#2412
1D
0G
0J
1M
1'
#2413
0E
0C
#2414
0'
1%
0$
#2415
1F
0I
0L
1O
1C
0B
0A
1(
#2417
1&
0%
1$
#2418
0O
0(
r2418 6
#2460
b110001 *
b110001 +
03
0#
b1001 4
r2460 5
08
#2462
1'
#2463
0F
0C
#2465
0&
r2465 6
#2510
b110010 *
b110010 +
b1001 0
b1001 2
13
b1001 "
1#
b1011 4
r2510 5
1@
18
#2512
0D
0'
#2513
1E
1C
#2514
1'
#2515
1&
r2515 6
#2560
b110011 *
b110011 +
03
0#
b1010 4
r2560 5
08
#2562
0'
r2562 6
#2610
b110100 *
b110100 +
b1010 0
b1010 2
13
b1010 "
1#
b1100 4
r2610 5
0@
1?
18
#2612
1D
1G
1'
#2613
0E
0C
#2614
0'
#2615
1F
1C
#2617
0&
#2618
1I
1B
#2620
1%
r2620 6
#2660
b110101 *
b110101 +
03
0#
b1011 4
r2660 5
08
#2662
1'
#2663
0F
0C
#2665
1&
#2666
0I
0B
#2668
0%
r2668 6
#2710
b110110 *
b110110 +
b1011 0
b1011 2
13
b1011 "
1#
b1101 4
r2710 5
1@
18
#2712
0D
0'
#2713
1E
1C
#2714
1'
#2715
0&
#2716
1I
1B
#2718
1%
r2718 6
#2760
b110111 *
b110111 +
03
0#
b1100 4
r2760 5
08
#2762
0'
r2762 6
#2810
b111000 *
b111000 +
b1100 0
b1100 2
13
b1100 "
1#
b1110 4
r2810 5
0@
0?
1>
18
#2812
1D
0G
1J
1'
#2813
0E
0C
#2814
0'
0%
#2815
1F
0I
1L
1C
0B
1A
#2817
1&
1%
0$
#2818
0L
1O
0A
1(
#2820
1$
#2821
0O
0(
r2821 6
#2860
b111001 *
b111001 +
03
0#
b1101 4
r2860 5
08
#2862
1'
#2863
0F
0C
#2865
0&
r2865 6
#2910
b111010 *
b111010 +
b1101 0
b1101 2
13
b1101 "
1#
b1111 4
r2910 5
1@
18
#2912
0D
0'
#2913
1E
1C
#2914
1'
#2915
1&
r2915 6
#2960
b111011 *
b111011 +
03
0#
b1110 4
r2960 5
08
#2962
0'
r2962 6
#3010
b111100 *
b111100 +
b1110 0
b1110 2
13
b1110 "
1#
b10000 4
r3010 5
0@
1?
18
#3012
1D
1G
1'
#3013
0E
0C
#3014
0'
#3015
1F
1C
#3017
0&
#3018
1I
1B
#3020
0%
#3021
1L
1A
#3023
0$
#3024
1O
1(
r3024 6
#3060
b111101 *
b111101 +
03
0#
b1111 4
r3060 5
08
#3062
1'
#3063
0F
0C
#3065
1&
#3066
0I
0B
#3068
1%
#3069
0L
0A
#3071
1$
#3072
0O
0(
r3072 6
#3110
b111110 *
b111110 +
b1111 0
b1111 2
13
b1111 "
1#
b10001 4
r3110 5
1@
18
#3112
0D
0'
#3113
1E
1C
#3114
1'
#3115
0&
#3116
1I
1B
#3118
0%
#3119
1L
1A
#3121
0$
#3122
1O
1(
r3122 6
#3160
b111111 *
b111111 +
03
0#
b10000 4
r3160 5
08
#3162
0'
r3162 6
#3210
b1000000 *
b1000000 +
b10000 0
b10 /
b0 0
b10 1
b0 2
13
b10 !
b0 "
1#
b11 4
r3210 5
0@
0?
0>
0=
0<
1;
18
#3212
0J
0M
1'
#3213
0E
0C
#3214
1%
1$
#3215
1&
0L
0O
0A
0(
#3216
0I
0B
#3217
0$
#3218
0%
r3218 6
#3260
b1000001 *
b1000001 +
03
0#
b10 4
r3260 5
08
#3262
0'
r3262 6
#3310
b1000010 *
b1000010 +
b1 0
b1 2
13
b1 "
1#
b100 4
r3310 5
1@
18
#3312
1D
1'
#3314
0'
#3315
1F
1C
#3317
0&
#3318
1I
1B
#3320
1%
r3320 6
#3360
b1000011 *
b1000011 +
03
0#
b11 4
r3360 5
08
#3362
1'
#3363
0F
0C
#3365
1&
#3366
0I
0B
#3368
0%
r3368 6
#3410
b1000100 *
b1000100 +
b10 0
b10 2
13
b10 "
1#
b101 4
r3410 5
0@
1?
18
#3412
0D
0G
0'
#3413
1H
1B
#3414
1'
0&
#3415
1%
r3415 6
#3460
b1000101 *
b1000101 +
03
0#
b100 4
r3460 5
08
#3462
0'
r3462 6
#3510
b1000110 *
b1000110 +
b11 0
b11 2
13
b11 "
1#
b110 4
r3510 5
1@
18
#3512
1D
1'
#3514
0'
#3515
1F
1C
#3517
1&
r3517 6
#3560
b1000111 *
b1000111 +
03
0#
b101 4
r3560 5
08
#3562
1'
#3563
0F
0C
#3565
0&
r3565 6
#3610
b1001000 *
b1001000 +
b100 0
b100 2
13
b100 "
1#
b111 4
r3610 5
0@
0?
1>
18
#3612
0D
1G
1J
0'
#3613
0H
0B
#3614
1'
1&
r3614 6
#3660
b1001001 *
b1001001 +
03
0#
b110 4
r3660 5
08
#3662
0'
r3662 6
#3710
b1001010 *
b1001010 +
b101 0
b101 2
13
b101 "
1#
b1000 4
r3710 5
1@
18
#3712
1D
1'
#3714
0'
#3715
1F
1C
#3717
0&
#3718
1I
1B
#3720
0%
#3721
1L
1A
#3723
1$
r3723 6
#3760
b1001011 *
b1001011 +
03
0#
b111 4
r3760 5
08
#3762
1'
#3763
0F
0C
#3765
1&
#3766
0I
0B
#3768
1%
#3769
0L
0A
#3771
0$
r3771 6
#3810
b1001100 *
b1001100 +
b110 0
b110 2
13
b110 "
1#
b1001 4
r3810 5
0@
1?
18
#3812
0D
0G
0'
#3813
1H
1B
#3814
1'
0&
#3815
0%
#3816
1L
1A
#3818
1$
r3818 6
#3860
b1001101 *
b1001101 +
03
0#
b1000 4
r3860 5
08
#3862
0'
r3862 6
#3910
b1001110 *
b1001110 +
b111 0
b111 2
13
b111 "
1#
b1010 4
r3910 5
1@
18
#3912
1D
1'
#3914
0'
#3915
1F
1C
#3917
1&
r3917 6
#3960
b1001111 *
b1001111 +
03
0#
b1001 4
r3960 5
08
#3962
1'
#3963
0F
0C
#3965
0&
r3965 6
#4010
b1010000 *
b1010000 +
b1000 0
b1000 2
13
b1000 "
1#
b1011 4
r4010 5
0@
0?
0>
1=
18
#4012
0D
1G
0J
1M
0'
#4013
0H
0B
#4014
1'
1&
0$
#4015
0L
1O
0A
1(
#4017
1$
#4018
0O
0(
r4018 6
#4060
b1010001 *
b1010001 +
03
0#
b1010 4
r4060 5
08
#4062
0'
r4062 6
#4110
b1010010 *
b1010010 +
b1001 0
b1001 2
13
b1001 "
1#
b1100 4
r4110 5
1@
18
#4112
1D
1'
#4114
0'
#4115
1F
1C
#4117
0&
#4118
1I
1B
#4120
1%
r4120 6
#4160
b1010011 *
b1010011 +
03
0#
b1011 4
r4160 5
08
#4162
1'
#4163
0F
0C
#4165
1&
#4166
0I
0B
#4168
0%
r4168 6
#4210
b1010100 *
b1010100 +
b1010 0
b1010 2
13
b1010 "
1#
b1101 4
r4210 5
0@
1?
18
#4212
0D
0G
0'
#4213
1H
1B
#4214
1'
0&
#4215
1%
r4215 6
#4260
b1010101 *
b1010101 +
03
0#
b1100 4
r4260 5
08
#4262
0'
r4262 6
#4310
b1010110 *
b1010110 +
b1011 0
b1011 2
13
b1011 "
1#
b1110 4
r4310 5
1@
18
#4312
1D
1'
#4314
0'
#4315
1F
1C
#4317
1&
r4317 6
#4360
b1010111 *
b1010111 +
03
0#
b1101 4
r4360 5
08
#4362
1'
#4363
0F
0C
#4365
0&
r4365 6
#4410
b1011000 *
b1011000 +
b1100 0
b1100 2
13
b1100 "
1#
b1111 4
r4410 5
0@
0?
1>
18
#4412
0D
1G
1J
0'
#4413
0H
0B
#4414
1'
1&
r4414 6
#4460
b1011001 *
b1011001 +
03
0#
b1110 4
r4460 5
08
#4462
0'
r4462 6
#4510
b1011010 *
b1011010 +
b1101 0
b1101 2
13
b1101 "
1#
b10000 4
r4510 5
1@
18
#4512
1D
1'
#4514
0'
#4515
1F
1C
#4517
0&
#4518
1I
1B
#4520
0%
#4521
1L
1A
#4523
0$
#4524
1O
1(
r4524 6
#4560
b1011011 *
b1011011 +
03
0#
b1111 4
r4560 5
08
#4562
1'
#4563
0F
0C
#4565
1&
#4566
0I
0B
#4568
1%
#4569
0L
0A
#4571
1$
#4572
0O
0(
r4572 6
#4610
b1011100 *
b1011100 +
b1110 0
b1110 2
13
b1110 "
1#
b10001 4
r4610 5
0@
1?
18
#4612
0D
0G
0'
#4613
1H
1B
#4614
1'
0&
#4615
0%
#4616
1L
1A
#4618
0$
#4619
1O
1(
r4619 6
#4660
b1011101 *
b1011101 +
03
0#
b10000 4
r4660 5
08
#4662
0'
r4662 6
#4710
b1011110 *
b1011110 +
b1111 0
b1111 2
13
b1111 "
1#
b10010 4
r4710 5
1@
18
#4712
1D
1'
#4714
0'
#4715
1F
1C
#4717
1&
r4717 6
#4760
b1011111 *
b1011111 +
03
0#
b10001 4
r4760 5
08
#4762
1'
#4763
0F
0C
#4765
0&
r4765 6
#4810
b1100000 *
b1100000 +
b10000 0
b11 /
b0 0
b11 1
b0 2
13
b11 !
b0 "
1#
b100 4
r4810 5
0@
0?
0>
0=
1<
18
#4812
1G
0J
0M
0'
#4813
0H
1F
0B
1C
#4814
1$
#4815
0L
0O
0A
0(
#4816
1I
1B
#4817
0$
#4818
1%
r4818 6
#4860
b1100001 *
b1100001 +
03
0#
b11 4
r4860 5
08
#4862
1'
#4863
0F
0C
#4865
1&
#4866
0I
0B
#4868
0%
r4868 6
#4910
b1100010 *
b1100010 +
b1 0
b1 2
13
b1 "
1#
b101 4
r4910 5
1@
18
#4912
0D
0'
#4913
1E
1C
#4914
1'
#4915
0&
#4916
1I
1B
#4918
1%
r4918 6
#4960
b1100011 *
b1100011 +
03
0#
b100 4
r4960 5
08
#4962
0'
r4962 6
#5010
b1100100 *
b1100100 +
b10 0
b10 2
13
b10 "
1#
b110 4
r5010 5
0@
1?
18
#5012
1D
0G
1'
#5013
0E
1H
0C
#5014
0'
#5015
1F
0I
1C
#5017
1&
r5017 6
#5060
b1100101 *
b1100101 +
03
0#
b101 4
r5060 5
08
#5062
1'
#5063
0F
0C
#5065
0&
r5065 6
#5110
b1100110 *
b1100110 +
b11 0
b11 2
13
b11 "
1#
b111 4
r5110 5
1@
18
#5112
0D
0'
#5113
1E
1C
#5114
1'
#5115
1&
r5115 6
#5160
b1100111 *
b1100111 +
03
0#
b110 4
r5160 5
08
#5162
0'
r5162 6
#5210
b1101000 *
b1101000 +
b100 0
b100 2
13
b100 "
1#
b1000 4
r5210 5
0@
0?
1>
18
#5212
1D
1G
1J
1'
#5213
0E
0H
0C
0B
#5214
0'
#5215
1F
1C
#5217
0&
#5218
1I
1B
#5220
0%
#5221
1L
1A
#5223
1$
r5223 6
#5260
b1101001 *
b1101001 +
03
0#
b111 4
r5260 5
08
#5262
1'
#5263
0F
0C
#5265
1&
#5266
0I
0B
#5268
1%
#5269
0L
0A
#5271
0$
r5271 6
#5310
b1101010 *
b1101010 +
b101 0
b101 2
13
b101 "
1#
b1001 4
r5310 5
1@
18
#5312
0D
0'
#5313
1E
1C
#5314
1'
#5315
0&
#5316
1I
1B
#5318
0%
#5319
1L
1A
#5321
1$
r5321 6
#5360
b1101011 *
b1101011 +
03
0#
b1000 4
r5360 5
08
#5362
0'
r5362 6
#5410
b1101100 *
b1101100 +
b110 0
b110 2
13
b110 "
1#
b1010 4
r5410 5
0@
1?
18
#5412
1D
0G
1'
#5413
0E
1H
0C
#5414
0'
#5415
1F
0I
1C
#5417
1&
r5417 6
#5460
b1101101 *
b1101101 +
03
0#
b1001 4
r5460 5
08
#5462
1'
#5463
0F
0C
#5465
0&
r5465 6
#5510
b1101110 *
b1101110 +
b111 0
b111 2
13
b111 "
1#
b1011 4
r5510 5
1@
18
#5512
0D
0'
#5513
1E
1C
#5514
1'
#5515
1&
r5515 6
#5560
b1101111 *
b1101111 +
03
0#
b1010 4
r5560 5
08
#5562
0'
r5562 6
#5610
b1110000 *
b1110000 +
b1000 0
b1000 2
13
b1000 "
1#
b1100 4
r5610 5
0@
0?
0>
1=
18
#5612
1D
1G
0J
1M
1'
#5613
0E
0H
0C
0B
#5614
0'
0$
#5615
1F
0L
1O
1C
0A
1(
#5617
0&
1$
#5618
1I
0O
1B
0(
#5620
1%
r5620 6
#5660
b1110001 *
b1110001 +
03
0#
b1011 4
r5660 5
08
#5662
1'
#5663
0F
0C
#5665
1&
#5666
0I
0B
#5668
0%
r5668 6
#5710
b1110010 *
b1110010 +
b1001 0
b1001 2
13
b1001 "
1#
b1101 4
r5710 5
1@
18
#5712
0D
0'
#5713
1E
1C
#5714
1'
#5715
0&
#5716
1I
1B
#5718
1%
r5718 6
#5760
b1110011 *
b1110011 +
03
0#
b1100 4
r5760 5
08
#5762
0'
r5762 6
#5810
b1110100 *
b1110100 +
b1010 0
b1010 2
13
b1010 "
1#
b1110 4
r5810 5
0@
1?
18
#5812
1D
0G
1'
#5813
0E
1H
0C
#5814
0'
#5815
1F
0I
1C
#5817
1&
r5817 6
#5860
b1110101 *
b1110101 +
03
0#
b1101 4
r5860 5
08
#5862
1'
#5863
0F
0C
#5865
0&
r5865 6
#5910
b1110110 *
b1110110 +
b1011 0
b1011 2
13
b1011 "
1#
b1111 4
r5910 5
1@
18
#5912
0D
0'
#5913
1E
1C
#5914
1'
#5915
1&
r5915 6
#5960
b1110111 *
b1110111 +
03
0#
b1110 4
r5960 5
08
#5962
0'
r5962 6
#6010
b1111000 *
b1111000 +
b1100 0
b1100 2
13
b1100 "
1#
b10000 4
r6010 5
0@
0?
1>
18
#6012
1D
1G
1J
1'
#6013
0E
0H
0C
0B
#6014
0'
#6015
1F
1C
#6017
0&
#6018
1I
1B
#6020
0%
#6021
1L
1A
#6023
0$
#6024
1O
1(
r6024 6
#6060
b1111001 *
b1111001 +
03
0#
b1111 4
r6060 5
08
#6062
1'
#6063
0F
0C
#6065
1&
#6066
0I
0B
#6068
1%
#6069
0L
0A
#6071
1$
#6072
0O
0(
r6072 6
#6110
b1111010 *
b1111010 +
b1101 0
b1101 2
13
b1101 "
1#
b10001 4
r6110 5
1@
18
#6112
0D
0'
#6113
1E
1C
#6114
1'
#6115
0&
#6116
1I
1B
#6118
0%
#6119
1L
1A
#6121
0$
#6122
1O
1(
r6122 6
#6160
b1111011 *
b1111011 +
03
0#
b10000 4
r6160 5
08
#6162
0'
r6162 6
#6210
b1111100 *
b1111100 +
b1110 0
b1110 2
13
b1110 "
1#
b10010 4
r6210 5
0@
1?
18
#6212
1D
0G
1'
#6213
0E
1H
0C
#6214
0'
#6215
1F
0I
1C
#6217
1&
r6217 6
#6260
b1111101 *
b1111101 +
03
0#
b10001 4
r6260 5
08
#6262
1'
#6263
0F
0C
